[
{
  "model": "articles.article",
  "pk": 2,
  "fields": {
    "title": "Meditation And Nature",
    "imageUrl": "https://cdn.mindful.org/ScienceOfMeditation.jpg?q=80&fm=jpg&fit=crop&w=1400&h=875",
    "text": "Lorem ipsum dolor sit amet, consectetur adipiscing elit. Etiam leo quam, rhoncus et turpis tempus, tempor blandit nulla. Donec eu libero non sem pulvinar condimentum. Morbi eget sapien sed mi tincidunt aliquet id sit amet urna. Donec vel enim tortor. Curabitur consequat, nisl nec sagittis fermentum, velit elit fermentum lacus, consequat ultrices lacus quam quis dolor. Quisque luctus orci justo, in blandit lorem hendrerit id. Sed suscipit ex ut lorem pharetra, ut laoreet purus molestie. Morbi in tincidunt ante. Cras sodales mi sit amet elit congue, id dignissim neque semper.Ut nec elementum metus. Duis aliquet nulla in nisi maximus ornare. Praesent sed elit blandit, laoreet mauris vitae, egestas elit. Curabitur id odio ut augue tempus feugiat nec sed leo. Maecenas commodo risus felis, id viverra ex malesuada in. Suspendisse laoreet placerat lacus. Donec id massa arcu. Suspendisse in nisi sed ante euismod ultricies. Sed dapibus, justo ut dapibus porta, eros urna pretium est, hendrerit finibus arcu libero sed eros. Proin sit amet ligula nec urna feugiat lacinia in at felis. Proin quis malesuada neque. Vestibulum ullamcorper vehicula urna ut commodo.Nulla fringilla orci nunc, vel ultricies enim maximus nec. Etiam semper, diam quis blandit laoreet, risus magna eleifend dolor, sed lobortis ex urna nec tellus. Curabitur maximus tortor varius lorem lacinia, eget consectetur lectus imperdiet. Nunc tempor lorem id sapien laoreet porta. Morbi nec ullamcorper justo. Suspendisse bibendum risus id augue accumsan, efficitur condimentum massa imperdiet. Donec imperdiet tempor dui, blandit facilisis dui facilisis sit amet. Aliquam erat risus, dignissim eget neque vitae, lacinia lacinia magna. Pellentesque habitant morbi tristique senectus et netus et malesuada fames ac turpis egestas.Nam venenatis, magna ut pellentesque maximus, massa nisl ullamcorper lorem, sed porta massa dui vel sapien. Nunc ut elementum nisi, ut maximus erat. Ut in turpis vel arcu interdum dapibus vitae nec tortor. Nunc et enim ac lectus porttitor fringilla. Nulla maximus elementum accumsan. Nullam hendrerit, quam sed tempus ornare, nunc massa dictum odio, eget maximus ligula neque sit amet purus. Maecenas pretium quam in ex suscipit, at finibus purus pretium. Donec erat arcu, vulputate at lacinia id, dictum id erat. Donec eget erat vel dolor blandit lacinia. Aliquam mollis sollicitudin lorem sed convallis. Phasellus at orci posuere, euismod eros eget, viverra duiNulla tincidunt mattis arcu, vel porttitor orci. Maecenas rutrum laoreet tortor at laoreet. Duis dictum commodo risus, at maximus nisi placerat id. Suspendisse dictum mauris lacus, sed dapibus urna dignissim sed. In ac mi sed ante volutpat placerat eu non urna. Phasellus porta lorem congue interdum finibus. Sed et turpis auctor, pretium ipsum id, consectetur augue. Vivamus id vestibulum eros. Aliquam euismod odio et est interdum, non sollicitudin massa sagittis. In ultricies eleifend dolor, eget elementum felis malesuada vel. Cras leo eros, blandit sit amet tincidunt vitae, porta eu ipsum. Quisque id iaculis neque.",
    "titleImageUrl": "https://nonprofits.agileventures.org/images/big_picture.jpg",
    "owner": 9
  }
},
{
  "model": "articles.article",
  "pk": 3,
  "fields": {
    "title": "Hiking, Relax and Training",
    "imageUrl": "https://www.highmountainguides.com/wp-content/uploads/2012/02/P9050695-e1512310988500.jpg",
    "text": "Lorem ipsum dolor sit amet, consectetur adipiscing elit. Etiam leo quam, rhoncus et turpis tempus, tempor blandit nulla. Donec eu libero non sem pulvinar condimentum. Morbi eget sapien sed mi tincidunt aliquet id sit amet urna. Donec vel enim tortor. Curabitur consequat, nisl nec sagittis fermentum, velit elit fermentum lacus, consequat ultrices lacus quam quis dolor. Quisque luctus orci justo, in blandit lorem hendrerit id. Sed suscipit ex ut lorem pharetra, ut laoreet purus molestie. Morbi in tincidunt ante. Cras sodales mi sit amet elit congue, id dignissim neque semper.Ut nec elementum metus. Duis aliquet nulla in nisi maximus ornare. Praesent sed elit blandit, laoreet mauris vitae, egestas elit. Curabitur id odio ut augue tempus feugiat nec sed leo. Maecenas commodo risus felis, id viverra ex malesuada in. Suspendisse laoreet placerat lacus. Donec id massa arcu. Suspendisse in nisi sed ante euismod ultricies. Sed dapibus, justo ut dapibus porta, eros urna pretium est, hendrerit finibus arcu libero sed eros. Proin sit amet ligula nec urna feugiat lacinia in at felis. Proin quis malesuada neque. Vestibulum ullamcorper vehicula urna ut commodo.Nulla fringilla orci nunc, vel ultricies enim maximus nec. Etiam semper, diam quis blandit laoreet, risus magna eleifend dolor, sed lobortis ex urna nec tellus. Curabitur maximus tortor varius lorem lacinia, eget consectetur lectus imperdiet. Nunc tempor lorem id sapien laoreet porta. Morbi nec ullamcorper justo. Suspendisse bibendum risus id augue accumsan, efficitur condimentum massa imperdiet. Donec imperdiet tempor dui, blandit facilisis dui facilisis sit amet. Aliquam erat risus, dignissim eget neque vitae, lacinia lacinia magna. Pellentesque habitant morbi tristique senectus et netus et malesuada fames ac turpis egestas.Nam venenatis, magna ut pellentesque maximus, massa nisl ullamcorper lorem, sed porta massa dui vel sapien. Nunc ut elementum nisi, ut maximus erat. Ut in turpis vel arcu interdum dapibus vitae nec tortor. Nunc et enim ac lectus porttitor fringilla. Nulla maximus elementum accumsan. Nullam hendrerit, quam sed tempus ornare, nunc massa dictum odio, eget maximus ligula neque sit amet purus. Maecenas pretium quam in ex suscipit, at finibus purus pretium. Donec erat arcu, vulputate at lacinia id, dictum id erat. Donec eget erat vel dolor blandit lacinia. Aliquam mollis sollicitudin lorem sed convallis. Phasellus at orci posuere, euismod eros eget, viverra duiNulla tincidunt mattis arcu, vel porttitor orci. Maecenas rutrum laoreet tortor at laoreet. Duis dictum commodo risus, at maximus nisi placerat id. Suspendisse dictum mauris lacus, sed dapibus urna dignissim sed. In ac mi sed ante volutpat placerat eu non urna. Phasellus porta lorem congue interdum finibus. Sed et turpis auctor, pretium ipsum id, consectetur augue. Vivamus id vestibulum eros. Aliquam euismod odio et est interdum, non sollicitudin massa sagittis. In ultricies eleifend dolor, eget elementum felis malesuada vel. Cras leo eros, blandit sit amet tincidunt vitae, porta eu ipsum. Quisque id iaculis neque.",
    "titleImageUrl": "https://lp-cms-production.imgix.net/2019-06/28206231.jpg?fit=crop&q=40&sharp=10&vib=20&auto=format&ixlib=react-8.6.4",
    "owner": 9
  }
},
{
  "model": "articles.article",
  "pk": 5,
  "fields": {
    "title": "So What is Crossfit?",
    "imageUrl": "https://media4.s-nbcnews.com/i/newscms/2019_43/3066896/191023-crossfit-ac-1153p_9e878640ddae8a030ef2e7754d3222be.jpg",
    "text": "Lorem ipsum dolor sit amet, consectetur adipiscing elit. Etiam leo quam, rhoncus et turpis tempus, tempor blandit nulla. Donec eu libero non sem pulvinar condimentum. Morbi eget sapien sed mi tincidunt aliquet id sit amet urna. Donec vel enim tortor. Curabitur consequat, nisl nec sagittis fermentum, velit elit fermentum lacus, consequat ultrices lacus quam quis dolor. Quisque luctus orci justo, in blandit lorem hendrerit id. Sed suscipit ex ut lorem pharetra, ut laoreet purus molestie. Morbi in tincidunt ante. Cras sodales mi sit amet elit congue, id dignissim neque semper.Ut nec elementum metus. Duis aliquet nulla in nisi maximus ornare. Praesent sed elit blandit, laoreet mauris vitae, egestas elit. Curabitur id odio ut augue tempus feugiat nec sed leo. Maecenas commodo risus felis, id viverra ex malesuada in. Suspendisse laoreet placerat lacus. Donec id massa arcu. Suspendisse in nisi sed ante euismod ultricies. Sed dapibus, justo ut dapibus porta, eros urna pretium est, hendrerit finibus arcu libero sed eros. Proin sit amet ligula nec urna feugiat lacinia in at felis. Proin quis malesuada neque. Vestibulum ullamcorper vehicula urna ut commodo.Nulla fringilla orci nunc, vel ultricies enim maximus nec. Etiam semper, diam quis blandit laoreet, risus magna eleifend dolor, sed lobortis ex urna nec tellus. Curabitur maximus tortor varius lorem lacinia, eget consectetur lectus imperdiet. Nunc tempor lorem id sapien laoreet porta. Morbi nec ullamcorper justo. Suspendisse bibendum risus id augue accumsan, efficitur condimentum massa imperdiet. Donec imperdiet tempor dui, blandit facilisis dui facilisis sit amet. Aliquam erat risus, dignissim eget neque vitae, lacinia lacinia magna. Pellentesque habitant morbi tristique senectus et netus et malesuada fames ac turpis egestas.Nam venenatis, magna ut pellentesque maximus, massa nisl ullamcorper lorem, sed porta massa dui vel sapien. Nunc ut elementum nisi, ut maximus erat. Ut in turpis vel arcu interdum dapibus vitae nec tortor. Nunc et enim ac lectus porttitor fringilla. Nulla maximus elementum accumsan. Nullam hendrerit, quam sed tempus ornare, nunc massa dictum odio, eget maximus ligula neque sit amet purus. Maecenas pretium quam in ex suscipit, at finibus purus pretium. Donec erat arcu, vulputate at lacinia id, dictum id erat. Donec eget erat vel dolor blandit lacinia. Aliquam mollis sollicitudin lorem sed convallis. Phasellus at orci posuere, euismod eros eget, viverra duiNulla tincidunt mattis arcu, vel porttitor orci. Maecenas rutrum laoreet tortor at laoreet. Duis dictum commodo risus, at maximus nisi placerat id. Suspendisse dictum mauris lacus, sed dapibus urna dignissim sed. In ac mi sed ante volutpat placerat eu non urna. Phasellus porta lorem congue interdum finibus. Sed et turpis auctor, pretium ipsum id, consectetur augue. Vivamus id vestibulum eros. Aliquam euismod odio et est interdum, non sollicitudin massa sagittis. In ultricies eleifend dolor, eget elementum felis malesuada vel. Cras leo eros, blandit sit amet tincidunt vitae, porta eu ipsum. Quisque id iaculis neque.",
    "titleImageUrl": "https://d1s2fu91rxnpt4.cloudfront.net/legacy/Games2012_CrossFitKilo_BigBob.jpeg",
    "owner": 9
  }
},
{
  "model": "articles.article",
  "pk": 6,
  "fields": {
    "title": "Why choose MMA?",
    "imageUrl": "https://i2.wp.com/www.bloodycanvas.net/wp-content/uploads/2020/06/Aleksander-Rakic.jpg?fit=1000%2C439&ssl=1",
    "text": "Lorem ipsum dolor sit amet, consectetur adipiscing elit. Suspendisse pellentesque pulvinar dapibus. Aliquam quis felis felis. In malesuada, neque in pellentesque posuere, dui leo faucibus ipsum, sit amet dignissim sapien lectus eget eros. Ut a neque non odio vehicula vehicula a non augue. Praesent consectetur blandit eros. Quisque non pretium ligula, et finibus velit. Phasellus id lectus lobortis, facilisis tellus luctus, ullamcorper nibh. Ut congue massa vitae dui faucibus, non fermentum nulla scelerisque. Quisque nec eros eu erat viverra imperdiet in lacinia nisi. Fusce elementum eros nec enim faucibus tincidunt. Donec in sapien ante. Aliquam sed luctus arcu.Fusce nec nulla placerat, finibus magna at, cursus nisl. In elementum nibh sed velit egestas, eget pellentesque dolor rhoncus. Duis quis dui magna. Nullam dapibus ut magna at vestibulum. Quisque ultricies euismod mi. Praesent facilisis enim in porta accumsan. Ut aliquam arcu in vehicula consectetur. Maecenas sit amet iaculis orci. Ut mattis justo sit amet urna egestas, vel luctus metus consectetur. Donec at sodales est. Pellentesque elementum sodales finibus. Morbi vulputate leo vel auctor ultrices.Etiam eget viverra diam, in mollis purus. Nam viverra, nibh ac dignissim scelerisque, lacus diam aliquet sapien, euismod egestas nisl orci tempor odio. Aenean posuere volutpat diam, a aliquam tortor. Aliquam vel dui sit amet neque accumsan ullamcorper non vitae lorem. Ut a dolor orci. Sed pharetra lectus orci, eu consectetur lacus congue hendrerit. Nam iaculis convallis est, vitae ultricies sem vulputate eu. Pellentesque at blandit ligula. Cras quam felis, accumsan ut feugiat quis, malesuada quis ipsum. Fusce at congue nunc, in rutrum nulla.Morbi suscipit libero turpis, ut pulvinar turpis pretium nec. Mauris varius nisi lacus. Curabitur condimentum neque at faucibus suscipit. Nulla dictum maximus eros nec faucibus. Fusce vestibulum eleifend tortor, nec lacinia justo cursus quis. Pellentesque pellentesque nisl eu libero mattis tincidunt. Duis dapibus dolor vel ultrices cursus. Sed pellentesque magna sed tellus pharetra ultricies. Mauris pharetra nisi vel augue maximus congue. Nam scelerisque in libero et dictum. Maecenas ac commodo tellus. Nullam convallis, turpis non faucibus viverra, dolor magna facilisis quam, ac commodo felis risus nec urna. Proin mi sapien, viverra vitae purus eu, placerat dapibus massa.",
    "titleImageUrl": "https://cdn.hipwallpaper.com/i/31/23/TFd0XS.jpg",
    "owner": 2
  }
},
{
  "model": "articles.article",
  "pk": 7,
  "fields": {
    "title": "How to Properly Stretch?",
    "imageUrl": "http://res.cloudinary.com/djq7pruxd/image/upload/v1592444105/images%20ykbhrn/vgfvlukhfskpoir7brje.jpg",
    "text": "Lorem ipsum dolor sit amet, consectetur adipiscing elit. Vivamus diam ligula, placerat sit amet tellus eget, tempor pretium justo. Maecenas consequat augue neque, et consequat nunc ullamcorper et. Quisque eget aliquam ex, nec varius nulla. Cras sed metus ut ex feugiat mattis ac vitae ligula. Nulla facilisi. Sed vestibulum lobortis nulla, vel euismod tortor rutrum ac. Aliquam ac erat hendrerit, lobortis libero sit amet, porta ex. Integer viverra, odio quis viverra posuere, lectus ex mattis lacus, eu dictum orci dolor a turpis. Aenean auctor sapien libero, et congue urna convallis et. Suspendisse lacinia felis nibh, et tempor nunc imperdiet ac. Aliquam sit amet bibendum odio.Donec ac odio a turpis tincidunt volutpat id vitae est. Curabitur rhoncus rhoncus mi id sodales. Sed porta in leo id efficitur. Praesent imperdiet tellus accumsan, consequat erat ac, condimentum diam. Fusce non nisl mi. Proin tempus consectetur diam quis eleifend. Mauris vulputate eget est ac volutpat.Nunc molestie nisl nec mauris facilisis pharetra in eu ex. Sed justo nulla, luctus eu gravida at, dapibus eget felis. In sit amet massa sapien. Vivamus id risus imperdiet, tincidunt est eget, blandit lectus. Cras imperdiet iaculis sapien ut suscipit. Vivamus at erat lorem. Nullam interdum dolor sit amet ante ullamcorper rutrum eget quis enim. Integer semper bibendum ante vel eleifend. Sed lobortis, metus nec rutrum congue, tortor augue porta est, ac volutpat arcu neque ut nunc. Duis id enim aliquam, malesuada nulla sed, mollis ex. Morbi volutpat erat nunc, vel faucibus magna interdum quis. Lorem ipsum dolor sit amet, consectetur adipiscing elit. Curabitur maximus velit id augue suscipit, et eleifend nulla pulvinar. Integer leo sem, bibendum a gravida eu, auctor non purus. Sed efficitur, odio efficitur fermentum vehicula, quam dolor bibendum nisl, sed cursus erat magna eget neque.Maecenas convallis nisl sem, sit amet iaculis orci hendrerit a. Etiam consectetur eu lorem ut eleifend. Pellentesque congue metus turpis, et finibus mauris eleifend sed. Aliquam erat volutpat. Nulla facilisi. Etiam tortor eros, mollis non vehicula vitae, feugiat vel sem. Aliquam ultricies auctor consequat. Integer nisi felis, euismod eu blandit nec, fermentum et lorem. Vestibulum et imperdiet quam, in scelerisque nunc. In venenatis diam massa, id facilisis leo porta vitae. Etiam mollis, urna sed dignissim euismod, diam metus molestie lacus, blandit egestas ligula enim ut metus. Vestibulum condimentum placerat lacinia. In aliquet risus eu odio finibus pulvinar.Nunc volutpat massa odio, non dignissim mauris commodo non. Integer sed molestie purus, dapibus accumsan risus. Cras facilisis, dolor id vehicula blandit, eros erat ullamcorper diam, eu commodo nisl ex non elit. Fusce in dui augue. Proin vehicula risus volutpat, euismod ante eu, volutpat nulla. Curabitur et dictum ante. Aenean gravida, justo ac accumsan semper, est eros placerat mauris, a finibus quam ligula a neque. In commodo sagittis erat nec consectetur. Donec aliquet finibus commodo. Etiam sed pharetra massa. Vivamus hendrerit, nulla sit amet pulvinar aliquam, ipsum nulla pretium ante, eget scelerisque ipsum dui in libero. Phasellus convallis sit amet neque vulputate mollis. Duis viverra, nibh et interdum venenatis, leo dui feugiat turpis, nec molestie ipsum ex eget erat.",
    "titleImageUrl": "https://stretch22.com/wp-content/uploads/2019/05/stretching-exercises-for-flex-flexibility.jpeg",
    "owner": 13
  }
}
]
